MANIFEST.in
README.rst
setup.cfg
setup.py
linecolor/__init__.py
linecolor/cmd.py
linecolor.egg-info/PKG-INFO
linecolor.egg-info/SOURCES.txt
linecolor.egg-info/dependency_links.txt
linecolor.egg-info/entry_points.txt
linecolor.egg-info/top_level.txt