Metadata-Version: 1.0
Name: linecolor
Version: 2017.3.22
Summary: small tool for colorful output of linux command
Home-page: https://github.com/sing1ee/linecolor
Author: zhangcheng
Author-email: zh.milo@gmail.com
License: MIT
Keywords: command-line-color,colorful output of linux command like tail,cat and ect.
Platform: UNKNOWN
